crunch64-0.5.1.dist-info/METADATA
crunch64-0.5.1.dist-info/WHEEL
crunch64/yaz0.pyi
crunch64/gzip.pyi
crunch64/yaz0.py
crunch64/__init__.py
crunch64/mio0.pyi
crunch64/gzip.py
crunch64/yay0.pyi
crunch64/crunch64.pyi
crunch64/mio0.py
crunch64/yay0.py
crunch64/py.typed
crunch64/crunch64.cpython-313-powerpc64le-linux-gnu.so
crunch64-0.5.1.dist-info/RECORD
