Metadata-Version: 2.4
Name: crunch64
Version: 0.5.1
Classifier: Programming Language :: Rust
Classifier: Programming Language :: Python :: Implementation :: CPython
Classifier: Programming Language :: Python :: Implementation :: PyPy
Summary: A library for handling common compression formats for N64 games
License: MIT
Requires-Python: >=3.9
Project-URL: Homepage, https://github.com/decompals/crunch64
Project-URL: Bug Tracker, https://github.com/decompals/crunch64/issues
